MANIFEST.in
README
compile.py
setup.py
qtsnbl/__init__.py
qtsnbl/axisitem.py
qtsnbl/cutslicewidget.py
qtsnbl/fixedwidget.py
qtsnbl/imageview.py
qtsnbl/resources.py
qtsnbl/updater.py
qtsnbl/version.py
qtsnbl/viewbox.py
qtsnbl/widgets.py
qtsnbl.egg-info/PKG-INFO
qtsnbl.egg-info/SOURCES.txt
qtsnbl.egg-info/dependency_links.txt
qtsnbl.egg-info/requires.txt
qtsnbl.egg-info/top_level.txt