Metadata-Version: 1.1
Name: qtsnbl
Version: 2017.11.20.1
Summary: PyQt widgets for SNBL programs
Home-page: https://hg.3lp.cx/qtsnbl
Author: Vadim Dyadkin
Author-email: dyadkin@gmail.com
License: GPLv3
Platform: UNKNOWN
Classifier: License :: OSI Approved :: GNU General Public License v3 (GPLv3)
Classifier: Programming Language :: Python
Classifier: Programming Language :: Python :: 3.6
Classifier: Programming Language :: Python :: Implementation :: CPython
